internal/__init__.py
internal/base_config.py
internal/base_factory.py
internal/common_enum/__init__.py
internal/common_enum/operator_type.py
internal/common_enum/order_type.py
internal/const.py
internal/database.py
internal/exception/__init__.py
internal/exception/base_exception.py
internal/exception/internal_exception.py
internal/ext/__init__.py
internal/ext/amazon/__init__.py
internal/ext/amazon/aws/__init__.py
internal/ext/amazon/aws/const.py
internal/http/__init__.py
internal/http/requests.py
internal/http/responses.py
internal/interface/__init__.py
internal/interface/base_interface.py
internal/middleware/__init__.py
internal/middleware/log_request.py
internal/model/__init__.py
internal/model/base_history_model.py
internal/model/base_model.py
internal/model/operate.py
internal/schema/__init__.py
internal/schema/base_schema.py
internal/utils.py
internal_rdbms-0.1.49.dist-info/METADATA
internal_rdbms-0.1.49.dist-info/WHEEL
internal_rdbms-0.1.49.dist-info/RECORD
