Metadata-Version: 2.3
Name: internal-rdbms
Version: 0.1.49
Summary: 
Author: Ray
Author-email: ray@cruisys.com
Requires-Python: >=3.11,<4.0
Classifier: Programming Language :: Python :: 3
Classifier: Programming Language :: Python :: 3.11
Classifier: Programming Language :: Python :: 3.12
Classifier: Programming Language :: Python :: 3.13
Requires-Dist: aiomysql (>=0.2.0,<0.3.0)
Requires-Dist: alembic (>=1.14.0,<2.0.0)
Requires-Dist: apscheduler (>=3.11.0,<4.0.0)
Requires-Dist: arrow (>=1.3.0,<2.0.0)
Requires-Dist: asgi-correlation-id (>=4.3.4,<5.0.0)
Requires-Dist: chardet (>=5.2.0,<6.0.0)
Requires-Dist: cryptography (>=44.0.0,<45.0.0)
Requires-Dist: dictdiffer (>=0.9.0,<0.10.0)
Requires-Dist: fastapi (>=0.115.6,<0.116.0)
Requires-Dist: greenlet (>=3.1.1,<4.0.0)
Requires-Dist: httpx (>=0.28.1,<0.29.0)
Requires-Dist: pillow (>=11.1.0,<12.0.0)
Requires-Dist: pillow-heif (>=0.21.0,<0.22.0)
Requires-Dist: pydantic-settings (>=2.7.1,<3.0.0)
Requires-Dist: python-jose (>=3.3.0,<4.0.0)
Requires-Dist: python-multipart (>=0.0.20,<0.0.21)
Requires-Dist: sqlalchemy (>=2.0.36,<3.0.0)
Requires-Dist: uvicorn (>=0.34.0,<0.35.0)
Requires-Dist: watchtower (>=3.3.1,<4.0.0)
